s3pypi/__init__.py
s3pypi/__main__.py
s3pypi/core.py
s3pypi/exceptions.py
s3pypi/index.py
s3pypi/locking.py
s3pypi/storage.py
s3pypi-2.0.1.dist-info/LICENSE
s3pypi-2.0.1.dist-info/METADATA
s3pypi-2.0.1.dist-info/WHEEL
s3pypi-2.0.1.dist-info/entry_points.txt
s3pypi-2.0.1.dist-info/RECORD
